icap/__init__.py
icap/_protocol.py
icap/async_icap.py
icap/exception.py
icap/icap.py
icap/py.typed
icap/response.py
icap/pytest_plugin/__init__.py
icap/pytest_plugin/builder.py
icap/pytest_plugin/mock.py
icap/pytest_plugin/plugin.py
icap/pytest_plugin/py.typed
python_icap-0.1.2.dist-info/METADATA
python_icap-0.1.2.dist-info/WHEEL
python_icap-0.1.2.dist-info/entry_points.txt
python_icap-0.1.2.dist-info/licenses/LICENSE
python_icap-0.1.2.dist-info/RECORD
