Metadata-Version: 2.4
Name: python-icap
Version: 0.1.2
Summary: Python ICAP (Internet Content Adaptation Protocol) Client
Project-URL: Homepage, https://github.com/CaptainDriftwood/python-icap
Project-URL: Repository, https://github.com/CaptainDriftwood/python-icap
Author: CaptainDriftwood
License: MIT
License-File: LICENSE
Keywords: antivirus,clamav,content-adaptation,icap,security,squid,virus-scanning
Classifier: Development Status :: 3 - Alpha
Classifier: Intended Audience :: Developers
Classifier: License :: OSI Approved :: MIT License
Classifier: Programming Language :: Python :: 3
Classifier: Programming Language :: Python :: 3.8
Classifier: Programming Language :: Python :: 3.9
Classifier: Programming Language :: Python :: 3.10
Classifier: Programming Language :: Python :: 3.11
Classifier: Programming Language :: Python :: 3.12
Classifier: Programming Language :: Python :: 3.13
Classifier: Programming Language :: Python :: 3.14
Classifier: Topic :: Internet :: WWW/HTTP
Classifier: Topic :: Software Development :: Libraries :: Python Modules
Requires-Python: >=3.8
